[
  {
    "id": "rJKAbDd_z",
    "companyId": "HJRa-DOuG",
    "title": "Frontend Developer",
    "description": "We are looking for a Frontend Developer familiar with React."
  },
  {
    "id": "SJRAZDu_z",
    "companyId": "HJRa-DOuG",
    "title": "Backend Developer",
    "description": "We are looking for a Backend Developer familiar with Node.js and Express."
  },
  {
    "id": "rkz1GwOOM",
    "companyId": "SJV0-wdOM",
    "title": "Full-Stack Developer",
    "description": "We are looking for a Full-Stack Developer familiar with Node.js, Express, and React."
  },
  {
    "id": "BkjmpAD5t",
    "companyId": "HJRa-DOuG",
    "title": "newTitle",
    "description": "this is a test"
  },
  {
    "id": "B1Nb0AvcY",
    "companyId": "HJRa-DOuG",
    "title": "newTitle2",
    "description": "this is a test"
  },
  {
    "id": "rkzMAAP5K",
    "companyId": "HJRa-DOuG",
    "title": "newTitle3",
    "description": "this is a test"
  },
  {
    "id": "BkaURADqY",
    "companyId": "HJRa-DOuG",
    "title": "newTitle4",
    "description": "this is a test"
  },
  {
    "id": "SkoFCAwqF",
    "companyId": "HJRa-DOuG",
    "title": "newTitle5",
    "description": "this is a test"
  },
  {
    "id": "HyG6ACPcY",
    "companyId": "HJRa-DOuG",
    "title": "newTitle5",
    "description": "this is a test"
  },
  {
    "id": "HyjxlyucF"
  },
  {
    "id": "H1_zey_5Y",
    "companyId": "HJRa-DOuG",
    "title": "newTitle5",
    "description": "this is a test"
  },
  {
    "id": "rJb7xku9Y",
    "companyId": "HJRa-DOuG",
    "title": "newTitle5",
    "description": "this is a test w/ input"
  },
  {
    "id": "rynqmJ_qt",
    "companyId": "HJRa-DOuG",
    "title": "newJobFromUI",
    "description": "This is a new job from the UI"
  },
  {
    "id": "r1FpXJu5Y",
    "companyId": "HJRa-DOuG",
    "title": "this is a new job from UI",
    "description": "ASdasdfasdf"
  },
  {
    "id": "S1YyIJt5t",
    "companyId": "HJRa-DOuG",
    "title": "newTitle5",
    "description": "this is a test w/ input"
  },
  {
    "id": "SJ6gIyYqK",
    "companyId": "HJRa-DOuG",
    "title": "newTitle5",
    "description": "this is a test w/ input"
  },
  {
    "id": "ByqzLktct",
    "companyId": "HJRa-DOuG",
    "title": "newTitle5",
    "description": "this is a test w/ input"
  },
  {
    "id": "BkrVIJK5F",
    "companyId": "HJRa-DOuG",
    "title": "newTitle5",
    "description": "this is a test w/ input"
  },
  {
    "id": "Bk6V8JtqF",
    "companyId": "HJRa-DOuG",
    "title": "newTitle5",
    "description": "this is a test w/ input"
  },
  {
    "id": "Sk_rLkFct",
    "companyId": "HJRa-DOuG",
    "title": "newTitle5",
    "description": "this is a test w/ input"
  },
  {
    "id": "SJkIUkYqK",
    "companyId": "HJRa-DOuG",
    "title": "newTitle5",
    "description": "this is a test w/ input"
  },
  {
    "id": "BkI881tqF",
    "companyId": "HJRa-DOuG",
    "title": "newTitle5",
    "description": "this is a test w/ input"
  },
  {
    "id": "r1eAL1FcK",
    "companyId": "HJRa-DOuG",
    "title": "newTitle5",
    "description": "this is a test w/ input"
  },
  {
    "id": "rkEfDJY9Y",
    "companyId": "HJRa-DOuG",
    "title": "newTitle5",
    "description": "this is a test w/ input"
  },
  {
    "id": "Bkep_kYcK",
    "companyId": "HJRa-DOuG",
    "title": "Tester",
    "description": "asdfasdf"
  },
  {
    "id": "rkLBjkt5t",
    "companyId": "HJRa-DOuG",
    "title": "newTitle5",
    "description": "this is a test w/ input"
  },
  {
    "id": "SJmIo1FqF",
    "companyId": "HJRa-DOuG",
    "title": "newTitle7",
    "description": "this is a test w/ input"
  },
  {
    "id": "r1ysnkKcY",
    "title": "newTitle7",
    "description": "this is a test w/ input",
    "companyId": "HJRa-DOuG"
  },
  {
    "id": "ByqepyKqF",
    "title": "PM",
    "description": "P those Ms ",
    "companyId": "HJRa-DOuG"
  },
  {
    "id": "rkgXpyt9t",
    "title": "Projext Ex",
    "description": "Mutants and what have you",
    "companyId": "SJV0-wdOM"
  },
  {
    "id": "BJRG9gtqK",
    "companyId": "SJV0-wdOM"
  },
  {
    "id": "BJ9DqgK5t",
    "title": "dfghjkl;'",
    "description": "",
    "companyId": "SJV0-wdOM"
  },
  {
    "id": "r1Mq5gK5Y",
    "title": "asdfasdfasdfs",
    "description": "f423542",
    "companyId": "SJV0-wdOM"
  },
  {
    "id": "S1fsqgF9t",
    "title": "7537863",
    "description": "786376387863",
    "companyId": "SJV0-wdOM"
  },
  {
    "id": "SyinogKqY",
    "title": "asdfasdf2352345345",
    "description": "aasdfasdfasdf",
    "companyId": "SJV0-wdOM"
  },
  {
    "id": "B13uhxtcF",
    "title": "new job 3",
    "description": "dsafsdf",
    "companyId": "SJV0-wdOM"
  },
  {
    "id": "ByijMfF5K",
    "title": "asdfasdf123123",
    "description": "asdfasdfasdf",
    "companyId": "SJV0-wdOM"
  },
  {
    "id": "SJHZQGtct",
    "title": "new post",
    "description": "asdfasdf",
    "companyId": "SJV0-wdOM"
  },
  {
    "id": "HkJc7ft9Y",
    "title": "asdfasdfasdfasdf",
    "description": "asdfasdf",
    "companyId": "SJV0-wdOM"
  },
  {
    "id": "HJ53mzY9K",
    "title": "new job wtf",
    "description": "wtf",
    "companyId": "SJV0-wdOM"
  },
  {
    "id": "S1ORQGt5K",
    "title": "new job wtf 2",
    "description": "wtf again",
    "companyId": "SJV0-wdOM"
  }
]